fuzzywuzzy/StringMatcher.py
fuzzywuzzy/__init__.py
fuzzywuzzy/fuzz.py
fuzzywuzzy/process.py
fuzzywuzzy/string_processing.py
fuzzywuzzy/utils.py
fuzzywuzzy-0.16.0.dist-info/DESCRIPTION.rst
fuzzywuzzy-0.16.0.dist-info/METADATA
fuzzywuzzy-0.16.0.dist-info/RECORD
fuzzywuzzy-0.16.0.dist-info/WHEEL
fuzzywuzzy-0.16.0.dist-info/metadata.json
fuzzywuzzy-0.16.0.dist-info/top_level.txt
fuzzywuzzy-0.16.0.dist-info/zip-safe
