Metadata-Version: 1.1
Name: fuzzywuzzy
Version: 0.16.0
Summary: Fuzzy string matching in python
Home-page: https://github.com/seatgeek/fuzzywuzzy
Author: Adam Cohen
Author-email: adam@seatgeek.com
License: GPL
Platform: UNKNOWN
Classifier: Intended Audience :: Developers
Classifier: Programming Language :: Python
Classifier: Programming Language :: Python :: 2.6
Classifier: Programming Language :: Python :: 2.7
Classifier: Programming Language :: Python :: 3
Classifier: Programming Language :: Python :: 3.3
Classifier: Programming Language :: Python :: 3.4
Classifier: Programming Language :: Python :: 3.5
Classifier: Programming Language :: Python :: 3.6
